alpaca_eval/__init__.py
alpaca_eval/analyze.py
alpaca_eval/completion_parsers.py
alpaca_eval/constants.py
alpaca_eval/main.py
alpaca_eval/plotting.py
alpaca_eval/processors.py
alpaca_eval/types.py
alpaca_eval/utils.py
alpaca_eval/annotators/__init__.py
alpaca_eval/annotators/base.py
alpaca_eval/annotators/pairwise_evaluator.py
alpaca_eval/decoders/__init__.py
alpaca_eval/decoders/anthropic.py
alpaca_eval/decoders/bedrock_anthropic.py
alpaca_eval/decoders/cache.py
alpaca_eval/decoders/cohere.py
alpaca_eval/decoders/google.py
alpaca_eval/decoders/huggingface_api.py
alpaca_eval/decoders/huggingface_local.py
alpaca_eval/decoders/jinachat.py
alpaca_eval/decoders/openai.py
alpaca_eval/decoders/replicate.py
alpaca_eval/decoders/test.py
alpaca_eval/decoders/vllm_local.py
alpaca_eval/evaluators_configs/README.md
alpaca_eval/evaluators_configs/Self-taught-llama3.1-70B-dpo/config.yaml
alpaca_eval/evaluators_configs/Self-taught-llama3.1-70B-dpo/self_taught.txt
alpaca_eval/evaluators_configs/alpaca_eval_clf_cot_gpt4_turbo/alpaca_eval_clf_cot.txt
alpaca_eval/evaluators_configs/alpaca_eval_clf_cot_gpt4_turbo/configs.yaml
alpaca_eval/evaluators_configs/alpaca_eval_clf_gpt4_turbo/alpaca_eval_clf.txt
alpaca_eval/evaluators_configs/alpaca_eval_clf_gpt4_turbo/configs.yaml
alpaca_eval/evaluators_configs/alpaca_eval_cot_gpt4_turbo_fn/alpaca_eval_fn.txt
alpaca_eval/evaluators_configs/alpaca_eval_cot_gpt4_turbo_fn/configs.yaml
alpaca_eval/evaluators_configs/alpaca_eval_gpt4/alpaca_eval.txt
alpaca_eval/evaluators_configs/alpaca_eval_gpt4/configs.yaml
alpaca_eval/evaluators_configs/alpaca_eval_gpt4_0314/configs.yaml
alpaca_eval/evaluators_configs/alpaca_eval_gpt4_0613/configs.yaml
alpaca_eval/evaluators_configs/alpaca_eval_gpt4_fn/alpaca_eval_fn.txt
alpaca_eval/evaluators_configs/alpaca_eval_gpt4_fn/configs.yaml
alpaca_eval/evaluators_configs/alpaca_eval_gpt4_turbo_fn/alpaca_eval_fn.txt
alpaca_eval/evaluators_configs/alpaca_eval_gpt4_turbo_fn/configs.yaml
alpaca_eval-0.6.6.dist-info/LICENSE
alpaca_eval-0.6.6.dist-info/METADATA
alpaca_eval-0.6.6.dist-info/WHEEL
alpaca_eval-0.6.6.dist-info/entry_points.txt
alpaca_eval-0.6.6.dist-info/top_level.txt
alpaca_eval-0.6.6.dist-info/RECORD
