Metadata-Version: 2.1
Name: alpaca_eval
Version: 0.6.6
Summary: AlpacaEval : An Automatic Evaluator of Instruction-following Models
Author: The Alpaca Team
Classifier: Intended Audience :: Developers
Classifier: Intended Audience :: Education
Classifier: Intended Audience :: Science/Research
Classifier: License :: OSI Approved :: Apache Software License
Classifier: Operating System :: OS Independent
Classifier: Programming Language :: Python :: 3.10
Classifier: Programming Language :: Python :: 3.11
Classifier: Programming Language :: Python :: 3.12
Classifier: Topic :: Scientific/Engineering :: Artificial Intelligence
Requires-Python: >=3.10
License-File: LICENSE
Requires-Dist: python-dotenv
Requires-Dist: datasets
Requires-Dist: openai>=1.5.0
Requires-Dist: pandas
Requires-Dist: tiktoken>=0.3.2
Requires-Dist: fire
Requires-Dist: scipy
Requires-Dist: huggingface_hub
Requires-Dist: patsy
Requires-Dist: scikit-learn
Provides-Extra: analysis
Requires-Dist: seaborn; extra == "analysis"
Requires-Dist: matplotlib; extra == "analysis"
Requires-Dist: jupyterlab; extra == "analysis"
Provides-Extra: dev
Requires-Dist: pre-commit>=3.2.0; extra == "dev"
Requires-Dist: black>=23.1.0; extra == "dev"
Requires-Dist: isort; extra == "dev"
Requires-Dist: pytest; extra == "dev"
Requires-Dist: pytest-mock; extra == "dev"
Requires-Dist: pytest-skip-slow; extra == "dev"
Requires-Dist: pytest-env; extra == "dev"
Requires-Dist: python-dotenv; extra == "dev"
Provides-Extra: local
Requires-Dist: accelerate; extra == "local"
Requires-Dist: transformers; extra == "local"
Requires-Dist: bitsandbytes; extra == "local"
Requires-Dist: torch; extra == "local"
Requires-Dist: xformers; extra == "local"
Requires-Dist: peft; extra == "local"
Requires-Dist: optimum; extra == "local"
Requires-Dist: einops; extra == "local"
Requires-Dist: vllm; extra == "local"
Provides-Extra: api
Requires-Dist: anthropic>=0.18; extra == "api"
Requires-Dist: cohere<5.0.0a0; extra == "api"
Requires-Dist: replicate; extra == "api"
Requires-Dist: boto3>=1.28.58; extra == "api"
Requires-Dist: google-generativeai; extra == "api"
Provides-Extra: all
Requires-Dist: accelerate; extra == "all"
Requires-Dist: transformers; extra == "all"
Requires-Dist: bitsandbytes; extra == "all"
Requires-Dist: torch; extra == "all"
Requires-Dist: xformers; extra == "all"
Requires-Dist: peft; extra == "all"
Requires-Dist: optimum; extra == "all"
Requires-Dist: einops; extra == "all"
Requires-Dist: vllm; extra == "all"
Requires-Dist: anthropic>=0.18; extra == "all"
Requires-Dist: cohere<5.0.0a0; extra == "all"
Requires-Dist: replicate; extra == "all"
Requires-Dist: boto3>=1.28.58; extra == "all"
Requires-Dist: google-generativeai; extra == "all"
Requires-Dist: seaborn; extra == "all"
Requires-Dist: matplotlib; extra == "all"
Requires-Dist: jupyterlab; extra == "all"
Requires-Dist: pre-commit>=3.2.0; extra == "all"
Requires-Dist: black>=23.1.0; extra == "all"
Requires-Dist: isort; extra == "all"
Requires-Dist: pytest; extra == "all"
Requires-Dist: pytest-mock; extra == "all"
Requires-Dist: pytest-skip-slow; extra == "all"
Requires-Dist: pytest-env; extra == "all"
Requires-Dist: python-dotenv; extra == "all"
